[{"Kind":"Interface","Namespace":"Windows.Services.Maps.LocalSearch","Name":"ILocalCategoriesStatics","Guid":"f49399f5-8261-4321-9974-ef92d49a8dca","Agile":false,"Properties":[{"Name":"All","Type":{"Kind":"Native","Name":"String"},"Accessors":["Getter"]},{"Name":"BankAndCreditUnions","Type":{"Kind":"Native","Name":"String"},"Accessors":["Getter"]},{"Name":"EatDrink","Type":{"Kind":"Native","Name":"String"},"Accessors":["Getter"]},{"Name":"Hospitals","Type":{"Kind":"Native","Name":"String"},"Accessors":["Getter"]},{"Name":"HotelsAndMotels","Type":{"Kind":"Native","Name":"String"},"Accessors":["Getter"]},{"Name":"Parking","Type":{"Kind":"Native","Name":"String"},"Accessors":["Getter"]},{"Name":"SeeDo","Type":{"Kind":"Native","Name":"String"},"Accessors":["Getter"]},{"Name":"Shop","Type":{"Kind":"Native","Name":"String"},"Accessors":["Getter"]}],"Methods":[{"Name":"get_BankAndCreditUnions","Static":false,"ReturnType":{"Kind":"Native","Name":"String"}},{"Name":"get_EatDrink","Static":false,"ReturnType":{"Kind":"Native","Name":"String"}},{"Name":"get_Hospitals","Static":false,"ReturnType":{"Kind":"Native","Name":"String"}},{"Name":"get_HotelsAndMotels","Static":false,"ReturnType":{"Kind":"Native","Name":"String"}},{"Name":"get_All","Static":false,"ReturnType":{"Kind":"Native","Name":"String"}},{"Name":"get_Parking","Static":false,"ReturnType":{"Kind":"Native","Name":"String"}},{"Name":"get_SeeDo","Static":false,"ReturnType":{"Kind":"Native","Name":"String"}},{"Name":"get_Shop","Static":false,"ReturnType":{"Kind":"Native","Name":"String"}}]},{"Kind":"Interface","Namespace":"Windows.Services.Maps.LocalSearch","Name":"ILocalLocation","Guid":"bb0fe9ab-4502-4f2c-94a9-0d60de0e2163","Agile":false,"Properties":[{"Name":"Address","Type":{"Namespace":"Windows.Services.Maps","Name":"MapAddress"},"Accessors":["Getter"]},{"Name":"DataAttribution","Type":{"Kind":"Native","Name":"String"},"Accessors":["Getter"]},{"Name":"Description","Type":{"Kind":"Native","Name":"String"},"Accessors":["Getter"]},{"Name":"DisplayName","Type":{"Kind":"Native","Name":"String"},"Accessors":["Getter"]},{"Name":"Identifier","Type":{"Kind":"Native","Name":"String"},"Accessors":["Getter"]},{"Name":"PhoneNumber","Type":{"Kind":"Native","Name":"String"},"Accessors":["Getter"]},{"Name":"Point","Type":{"Namespace":"Windows.Devices.Geolocation","Name":"Geopoint"},"Accessors":["Getter"]}],"Methods":[{"Name":"get_Address","Static":false,"ReturnType":{"Namespace":"Windows.Services.Maps","Name":"MapAddress"}},{"Name":"get_Identifier","Static":false,"ReturnType":{"Kind":"Native","Name":"String"}},{"Name":"get_Description","Static":false,"ReturnType":{"Kind":"Native","Name":"String"}},{"Name":"get_DisplayName","Static":false,"ReturnType":{"Kind":"Native","Name":"String"}},{"Name":"get_Point","Static":false,"ReturnType":{"Namespace":"Windows.Devices.Geolocation","Name":"Geopoint"}},{"Name":"get_PhoneNumber","Static":false,"ReturnType":{"Kind":"Native","Name":"String"}},{"Name":"get_DataAttribution","Static":false,"ReturnType":{"Kind":"Native","Name":"String"}}]},{"Kind":"Interface","Namespace":"Windows.Services.Maps.LocalSearch","Name":"ILocalLocation2","Guid":"6e9e307c-ecb5-4ffc-bb8c-ba50ba8c2dc6","Agile":false,"Properties":[{"Name":"Category","Type":{"Kind":"Native","Name":"String"},"Accessors":["Getter"]},{"Name":"HoursOfOperation","Type":{"Namespace":"Windows.Foundation.Collections","Name":"IVectorView","GenericArguments":[{"Namespace":"Windows.Services.Maps.LocalSearch","Name":"LocalLocationHoursOfOperationItem"}]},"Accessors":["Getter"]},{"Name":"RatingInfo","Type":{"Namespace":"Windows.Services.Maps.LocalSearch","Name":"LocalLocationRatingInfo"},"Accessors":["Getter"]}],"Methods":[{"Name":"get_Category","Static":false,"ReturnType":{"Kind":"Native","Name":"String"}},{"Name":"get_RatingInfo","Static":false,"ReturnType":{"Namespace":"Windows.Services.Maps.LocalSearch","Name":"LocalLocationRatingInfo"}},{"Name":"get_HoursOfOperation","Static":false,"ReturnType":{"Namespace":"Windows.Foundation.Collections","Name":"IVectorView","GenericArguments":[{"Namespace":"Windows.Services.Maps.LocalSearch","Name":"LocalLocationHoursOfOperationItem"}]}}]},{"Kind":"Interface","Namespace":"Windows.Services.Maps.LocalSearch","Name":"ILocalLocationFinderResult","Guid":"d09b6cc6-f338-4191-9fd8-5440b9a68f52","Agile":false,"Properties":[{"Name":"LocalLocations","Type":{"Namespace":"Windows.Foundation.Collections","Name":"IVectorView","GenericArguments":[{"Namespace":"Windows.Services.Maps.LocalSearch","Name":"LocalLocation"}]},"Accessors":["Getter"]},{"Name":"Status","Type":{"Namespace":"Windows.Services.Maps.LocalSearch","Name":"LocalLocationFinderStatus"},"Accessors":["Getter"]}],"Methods":[{"Name":"get_LocalLocations","Static":false,"ReturnType":{"Namespace":"Windows.Foundation.Collections","Name":"IVectorView","GenericArguments":[{"Namespace":"Windows.Services.Maps.LocalSearch","Name":"LocalLocation"}]}},{"Name":"get_Status","Static":false,"ReturnType":{"Namespace":"Windows.Services.Maps.LocalSearch","Name":"LocalLocationFinderStatus"}}]},{"Kind":"Interface","Namespace":"Windows.Services.Maps.LocalSearch","Name":"ILocalLocationFinderStatics","Guid":"d2ef7344-a0de-48ca-81a8-07c7dcfd37ab","Agile":false,"Methods":[{"Name":"FindLocalLocationsAsync","Static":false,"Parameters":[{"Name":"searchTerm","Type":{"Kind":"Native","Name":"String"},"Attributes":["In"]},{"Name":"searchArea","Type":{"Namespace":"Windows.Devices.Geolocation","Name":"Geocircle"},"Attributes":["In"]},{"Name":"localCategory","Type":{"Kind":"Native","Name":"String"},"Attributes":["In"]},{"Name":"maxResults","Type":{"Kind":"Native","Name":"UInt32"},"Attributes":["In"]}],"ReturnType":{"Namespace":"Windows.Foundation","Name":"IAsyncOperation","GenericArguments":[{"Namespace":"Windows.Services.Maps.LocalSearch","Name":"LocalLocationFinderResult"}]}}]},{"Kind":"Interface","Namespace":"Windows.Services.Maps.LocalSearch","Name":"ILocalLocationHoursOfOperationItem","Guid":"23548c72-a1c7-43f1-a4f0-1091c39ec640","Agile":false,"Properties":[{"Name":"Day","Type":{"Namespace":"Windows.Globalization","Name":"DayOfWeek"},"Accessors":["Getter"]},{"Name":"Span","Type":{"Namespace":"Windows.Foundation","Name":"TimeSpan"},"Accessors":["Getter"]},{"Name":"Start","Type":{"Namespace":"Windows.Foundation","Name":"TimeSpan"},"Accessors":["Getter"]}],"Methods":[{"Name":"get_Day","Static":false,"ReturnType":{"Namespace":"Windows.Globalization","Name":"DayOfWeek"}},{"Name":"get_Start","Static":false,"ReturnType":{"Namespace":"Windows.Foundation","Name":"TimeSpan"}},{"Name":"get_Span","Static":false,"ReturnType":{"Namespace":"Windows.Foundation","Name":"TimeSpan"}}]},{"Kind":"Interface","Namespace":"Windows.Services.Maps.LocalSearch","Name":"ILocalLocationRatingInfo","Guid":"cb1dab56-3354-4311-8bc0-a2d4d5eb806e","Agile":false,"Properties":[{"Name":"AggregateRating","Type":{"Namespace":"Windows.Foundation","Name":"IReference","GenericArguments":[{"Kind":"Native","Name":"Double"}]},"Accessors":["Getter"]},{"Name":"ProviderIdentifier","Type":{"Kind":"Native","Name":"String"},"Accessors":["Getter"]},{"Name":"RatingCount","Type":{"Namespace":"Windows.Foundation","Name":"IReference","GenericArguments":[{"Kind":"Native","Name":"Int32"}]},"Accessors":["Getter"]}],"Methods":[{"Name":"get_AggregateRating","Static":false,"ReturnType":{"Namespace":"Windows.Foundation","Name":"IReference","GenericArguments":[{"Kind":"Native","Name":"Double"}]}},{"Name":"get_RatingCount","Static":false,"ReturnType":{"Namespace":"Windows.Foundation","Name":"IReference","GenericArguments":[{"Kind":"Native","Name":"Int32"}]}},{"Name":"get_ProviderIdentifier","Static":false,"ReturnType":{"Kind":"Native","Name":"String"}}]},{"Kind":"Interface","Namespace":"Windows.Services.Maps.LocalSearch","Name":"IPlaceInfoHelperStatics","Guid":"dd1ca9a7-a9c6-491b-bc09-e80fcea48ee6","Agile":false,"Methods":[{"Name":"CreateFromLocalLocation","Static":false,"Parameters":[{"Name":"location","Type":{"Namespace":"Windows.Services.Maps.LocalSearch","Name":"LocalLocation"},"Attributes":["In"]}],"ReturnType":{"Namespace":"Windows.Services.Maps","Name":"PlaceInfo"}}]},{"Kind":"Class","Namespace":"Windows.Services.Maps.LocalSearch","Name":"LocalCategories","Agile":true,"BaseType":{"Namespace":"System","Name":"Object"},"Factory":{"Statics":[{"Name":"ILocalCategoriesStatics","Namespace":"Windows.Services.Maps.LocalSearch"}],"HasDefault":false},"Properties":[{"Name":"All","Type":{"Kind":"Native","Name":"String"},"Accessors":["Getter"]},{"Name":"BankAndCreditUnions","Type":{"Kind":"Native","Name":"String"},"Accessors":["Getter"]},{"Name":"EatDrink","Type":{"Kind":"Native","Name":"String"},"Accessors":["Getter"]},{"Name":"Hospitals","Type":{"Kind":"Native","Name":"String"},"Accessors":["Getter"]},{"Name":"HotelsAndMotels","Type":{"Kind":"Native","Name":"String"},"Accessors":["Getter"]},{"Name":"Parking","Type":{"Kind":"Native","Name":"String"},"Accessors":["Getter"]},{"Name":"SeeDo","Type":{"Kind":"Native","Name":"String"},"Accessors":["Getter"]},{"Name":"Shop","Type":{"Kind":"Native","Name":"String"},"Accessors":["Getter"]}],"Methods":[{"Name":"get_BankAndCreditUnions","Static":true,"ReturnType":{"Kind":"Native","Name":"String"}},{"Name":"get_EatDrink","Static":true,"ReturnType":{"Kind":"Native","Name":"String"}},{"Name":"get_Hospitals","Static":true,"ReturnType":{"Kind":"Native","Name":"String"}},{"Name":"get_HotelsAndMotels","Static":true,"ReturnType":{"Kind":"Native","Name":"String"}},{"Name":"get_All","Static":true,"ReturnType":{"Kind":"Native","Name":"String"}},{"Name":"get_Parking","Static":true,"ReturnType":{"Kind":"Native","Name":"String"}},{"Name":"get_SeeDo","Static":true,"ReturnType":{"Kind":"Native","Name":"String"}},{"Name":"get_Shop","Static":true,"ReturnType":{"Kind":"Native","Name":"String"}}]},{"Kind":"Class","Namespace":"Windows.Services.Maps.LocalSearch","Name":"LocalLocation","Agile":true,"BaseType":{"Namespace":"System","Name":"Object"},"DefaultInterface":{"Name":"ILocalLocation","Namespace":"Windows.Services.Maps.LocalSearch"},"Interfaces":[{"Name":"ILocalLocation","Namespace":"Windows.Services.Maps.LocalSearch"},{"Name":"ILocalLocation2","Namespace":"Windows.Services.Maps.LocalSearch"}],"Properties":[{"Name":"Address","Type":{"Namespace":"Windows.Services.Maps","Name":"MapAddress"},"Accessors":["Getter"]},{"Name":"DataAttribution","Type":{"Kind":"Native","Name":"String"},"Accessors":["Getter"]},{"Name":"Description","Type":{"Kind":"Native","Name":"String"},"Accessors":["Getter"]},{"Name":"DisplayName","Type":{"Kind":"Native","Name":"String"},"Accessors":["Getter"]},{"Name":"Identifier","Type":{"Kind":"Native","Name":"String"},"Accessors":["Getter"]},{"Name":"PhoneNumber","Type":{"Kind":"Native","Name":"String"},"Accessors":["Getter"]},{"Name":"Point","Type":{"Namespace":"Windows.Devices.Geolocation","Name":"Geopoint"},"Accessors":["Getter"]},{"Name":"Category","Type":{"Kind":"Native","Name":"String"},"Accessors":["Getter"]},{"Name":"HoursOfOperation","Type":{"Namespace":"Windows.Foundation.Collections","Name":"IVectorView","GenericArguments":[{"Namespace":"Windows.Services.Maps.LocalSearch","Name":"LocalLocationHoursOfOperationItem"}]},"Accessors":["Getter"]},{"Name":"RatingInfo","Type":{"Namespace":"Windows.Services.Maps.LocalSearch","Name":"LocalLocationRatingInfo"},"Accessors":["Getter"]}],"Methods":[{"Name":"get_Address","Static":false,"ReturnType":{"Namespace":"Windows.Services.Maps","Name":"MapAddress"}},{"Name":"get_Identifier","Static":false,"ReturnType":{"Kind":"Native","Name":"String"}},{"Name":"get_Description","Static":false,"ReturnType":{"Kind":"Native","Name":"String"}},{"Name":"get_DisplayName","Static":false,"ReturnType":{"Kind":"Native","Name":"String"}},{"Name":"get_Point","Static":false,"ReturnType":{"Namespace":"Windows.Devices.Geolocation","Name":"Geopoint"}},{"Name":"get_PhoneNumber","Static":false,"ReturnType":{"Kind":"Native","Name":"String"}},{"Name":"get_DataAttribution","Static":false,"ReturnType":{"Kind":"Native","Name":"String"}},{"Name":"get_Category","Static":false,"ReturnType":{"Kind":"Native","Name":"String"}},{"Name":"get_RatingInfo","Static":false,"ReturnType":{"Namespace":"Windows.Services.Maps.LocalSearch","Name":"LocalLocationRatingInfo"}},{"Name":"get_HoursOfOperation","Static":false,"ReturnType":{"Namespace":"Windows.Foundation.Collections","Name":"IVectorView","GenericArguments":[{"Namespace":"Windows.Services.Maps.LocalSearch","Name":"LocalLocationHoursOfOperationItem"}]}}]},{"Kind":"Class","Namespace":"Windows.Services.Maps.LocalSearch","Name":"LocalLocationFinder","Agile":true,"BaseType":{"Namespace":"System","Name":"Object"},"Factory":{"Statics":[{"Name":"ILocalLocationFinderStatics","Namespace":"Windows.Services.Maps.LocalSearch"}],"HasDefault":false},"Methods":[{"Name":"FindLocalLocationsAsync","Static":true,"Parameters":[{"Name":"searchTerm","Type":{"Kind":"Native","Name":"String"},"Attributes":["In"]},{"Name":"searchArea","Type":{"Namespace":"Windows.Devices.Geolocation","Name":"Geocircle"},"Attributes":["In"]},{"Name":"localCategory","Type":{"Kind":"Native","Name":"String"},"Attributes":["In"]},{"Name":"maxResults","Type":{"Kind":"Native","Name":"UInt32"},"Attributes":["In"]}],"ReturnType":{"Namespace":"Windows.Foundation","Name":"IAsyncOperation","GenericArguments":[{"Namespace":"Windows.Services.Maps.LocalSearch","Name":"LocalLocationFinderResult"}]}}]},{"Kind":"Class","Namespace":"Windows.Services.Maps.LocalSearch","Name":"LocalLocationFinderResult","Agile":true,"BaseType":{"Namespace":"System","Name":"Object"},"DefaultInterface":{"Name":"ILocalLocationFinderResult","Namespace":"Windows.Services.Maps.LocalSearch"},"Interfaces":[{"Name":"ILocalLocationFinderResult","Namespace":"Windows.Services.Maps.LocalSearch"}],"Properties":[{"Name":"LocalLocations","Type":{"Namespace":"Windows.Foundation.Collections","Name":"IVectorView","GenericArguments":[{"Namespace":"Windows.Services.Maps.LocalSearch","Name":"LocalLocation"}]},"Accessors":["Getter"]},{"Name":"Status","Type":{"Namespace":"Windows.Services.Maps.LocalSearch","Name":"LocalLocationFinderStatus"},"Accessors":["Getter"]}],"Methods":[{"Name":"get_LocalLocations","Static":false,"ReturnType":{"Namespace":"Windows.Foundation.Collections","Name":"IVectorView","GenericArguments":[{"Namespace":"Windows.Services.Maps.LocalSearch","Name":"LocalLocation"}]}},{"Name":"get_Status","Static":false,"ReturnType":{"Namespace":"Windows.Services.Maps.LocalSearch","Name":"LocalLocationFinderStatus"}}]},{"Kind":"Enum","Namespace":"Windows.Services.Maps.LocalSearch","Name":"LocalLocationFinderStatus","Agile":false,"BaseType":{"Kind":"Enum","Namespace":"System","Name":"Enum"},"Values":[{"Name":"Success","Value":0},{"Name":"UnknownError","Value":1},{"Name":"InvalidCredentials","Value":2},{"Name":"InvalidCategory","Value":3},{"Name":"InvalidSearchTerm","Value":4},{"Name":"InvalidSearchArea","Value":5},{"Name":"NetworkFailure","Value":6},{"Name":"NotSupported","Value":7}]},{"Kind":"Class","Namespace":"Windows.Services.Maps.LocalSearch","Name":"LocalLocationHoursOfOperationItem","Agile":true,"BaseType":{"Namespace":"System","Name":"Object"},"DefaultInterface":{"Name":"ILocalLocationHoursOfOperationItem","Namespace":"Windows.Services.Maps.LocalSearch"},"Interfaces":[{"Name":"ILocalLocationHoursOfOperationItem","Namespace":"Windows.Services.Maps.LocalSearch"}],"Properties":[{"Name":"Day","Type":{"Namespace":"Windows.Globalization","Name":"DayOfWeek"},"Accessors":["Getter"]},{"Name":"Span","Type":{"Namespace":"Windows.Foundation","Name":"TimeSpan"},"Accessors":["Getter"]},{"Name":"Start","Type":{"Namespace":"Windows.Foundation","Name":"TimeSpan"},"Accessors":["Getter"]}],"Methods":[{"Name":"get_Day","Static":false,"ReturnType":{"Namespace":"Windows.Globalization","Name":"DayOfWeek"}},{"Name":"get_Start","Static":false,"ReturnType":{"Namespace":"Windows.Foundation","Name":"TimeSpan"}},{"Name":"get_Span","Static":false,"ReturnType":{"Namespace":"Windows.Foundation","Name":"TimeSpan"}}]},{"Kind":"Class","Namespace":"Windows.Services.Maps.LocalSearch","Name":"LocalLocationRatingInfo","Agile":true,"BaseType":{"Namespace":"System","Name":"Object"},"DefaultInterface":{"Name":"ILocalLocationRatingInfo","Namespace":"Windows.Services.Maps.LocalSearch"},"Interfaces":[{"Name":"ILocalLocationRatingInfo","Namespace":"Windows.Services.Maps.LocalSearch"}],"Properties":[{"Name":"AggregateRating","Type":{"Namespace":"Windows.Foundation","Name":"IReference","GenericArguments":[{"Kind":"Native","Name":"Double"}]},"Accessors":["Getter"]},{"Name":"ProviderIdentifier","Type":{"Kind":"Native","Name":"String"},"Accessors":["Getter"]},{"Name":"RatingCount","Type":{"Namespace":"Windows.Foundation","Name":"IReference","GenericArguments":[{"Kind":"Native","Name":"Int32"}]},"Accessors":["Getter"]}],"Methods":[{"Name":"get_AggregateRating","Static":false,"ReturnType":{"Namespace":"Windows.Foundation","Name":"IReference","GenericArguments":[{"Kind":"Native","Name":"Double"}]}},{"Name":"get_RatingCount","Static":false,"ReturnType":{"Namespace":"Windows.Foundation","Name":"IReference","GenericArguments":[{"Kind":"Native","Name":"Int32"}]}},{"Name":"get_ProviderIdentifier","Static":false,"ReturnType":{"Kind":"Native","Name":"String"}}]},{"Kind":"Class","Namespace":"Windows.Services.Maps.LocalSearch","Name":"PlaceInfoHelper","Agile":true,"BaseType":{"Namespace":"System","Name":"Object"},"Factory":{"Statics":[{"Name":"IPlaceInfoHelperStatics","Namespace":"Windows.Services.Maps.LocalSearch"}],"HasDefault":false},"Methods":[{"Name":"CreateFromLocalLocation","Static":true,"Parameters":[{"Name":"location","Type":{"Namespace":"Windows.Services.Maps.LocalSearch","Name":"LocalLocation"},"Attributes":["In"]}],"ReturnType":{"Namespace":"Windows.Services.Maps","Name":"PlaceInfo"}}]}]