[{"Kind":"Class","Namespace":"Windows.Devices.Background","Name":"DeviceServicingDetails","Agile":true,"BaseType":{"Namespace":"System","Name":"Object"},"DefaultInterface":{"Name":"IDeviceServicingDetails","Namespace":"Windows.Devices.Background"},"Interfaces":[{"Name":"IDeviceServicingDetails","Namespace":"Windows.Devices.Background"}],"Properties":[{"Name":"Arguments","Type":{"Kind":"Native","Name":"String"},"Accessors":["Getter"]},{"Name":"DeviceId","Type":{"Kind":"Native","Name":"String"},"Accessors":["Getter"]},{"Name":"ExpectedDuration","Type":{"Namespace":"Windows.Foundation","Name":"TimeSpan"},"Accessors":["Getter"]}],"Methods":[{"Name":"get_DeviceId","Static":false,"ReturnType":{"Kind":"Native","Name":"String"}},{"Name":"get_Arguments","Static":false,"ReturnType":{"Kind":"Native","Name":"String"}},{"Name":"get_ExpectedDuration","Static":false,"ReturnType":{"Namespace":"Windows.Foundation","Name":"TimeSpan"}}]},{"Kind":"Class","Namespace":"Windows.Devices.Background","Name":"DeviceUseDetails","Agile":true,"BaseType":{"Namespace":"System","Name":"Object"},"DefaultInterface":{"Name":"IDeviceUseDetails","Namespace":"Windows.Devices.Background"},"Interfaces":[{"Name":"IDeviceUseDetails","Namespace":"Windows.Devices.Background"}],"Properties":[{"Name":"Arguments","Type":{"Kind":"Native","Name":"String"},"Accessors":["Getter"]},{"Name":"DeviceId","Type":{"Kind":"Native","Name":"String"},"Accessors":["Getter"]}],"Methods":[{"Name":"get_DeviceId","Static":false,"ReturnType":{"Kind":"Native","Name":"String"}},{"Name":"get_Arguments","Static":false,"ReturnType":{"Kind":"Native","Name":"String"}}]},{"Kind":"Interface","Namespace":"Windows.Devices.Background","Name":"IDeviceServicingDetails","Guid":"4aabee29-2344-4ac4-8527-4a8ef6905645","Agile":false,"Properties":[{"Name":"Arguments","Type":{"Kind":"Native","Name":"String"},"Accessors":["Getter"]},{"Name":"DeviceId","Type":{"Kind":"Native","Name":"String"},"Accessors":["Getter"]},{"Name":"ExpectedDuration","Type":{"Namespace":"Windows.Foundation","Name":"TimeSpan"},"Accessors":["Getter"]}],"Methods":[{"Name":"get_DeviceId","Static":false,"ReturnType":{"Kind":"Native","Name":"String"}},{"Name":"get_Arguments","Static":false,"ReturnType":{"Kind":"Native","Name":"String"}},{"Name":"get_ExpectedDuration","Static":false,"ReturnType":{"Namespace":"Windows.Foundation","Name":"TimeSpan"}}]},{"Kind":"Interface","Namespace":"Windows.Devices.Background","Name":"IDeviceUseDetails","Guid":"7d565141-557e-4154-b994-e4f7a11fb323","Agile":false,"Properties":[{"Name":"Arguments","Type":{"Kind":"Native","Name":"String"},"Accessors":["Getter"]},{"Name":"DeviceId","Type":{"Kind":"Native","Name":"String"},"Accessors":["Getter"]}],"Methods":[{"Name":"get_DeviceId","Static":false,"ReturnType":{"Kind":"Native","Name":"String"}},{"Name":"get_Arguments","Static":false,"ReturnType":{"Kind":"Native","Name":"String"}}]}]