[{"Kind":"Interface","Namespace":"Windows.Devices.Bluetooth.Rfcomm","Name":"IRfcommDeviceService","Guid":"ae81ff1f-c5a1-4c40-8c28-f3efd69062f3","Agile":false,"Properties":[{"Name":"ConnectionHostName","Type":{"Namespace":"Windows.Networking","Name":"HostName"},"Accessors":["Getter"]},{"Name":"ConnectionServiceName","Type":{"Kind":"Native","Name":"String"},"Accessors":["Getter"]},{"Name":"MaxProtectionLevel","Type":{"Namespace":"Windows.Networking.Sockets","Name":"SocketProtectionLevel"},"Accessors":["Getter"]},{"Name":"ProtectionLevel","Type":{"Namespace":"Windows.Networking.Sockets","Name":"SocketProtectionLevel"},"Accessors":["Getter"]},{"Name":"ServiceId","Type":{"Namespace":"Windows.Devices.Bluetooth.Rfcomm","Name":"RfcommServiceId"},"Accessors":["Getter"]}],"Methods":[{"Name":"get_ConnectionHostName","Static":false,"ReturnType":{"Namespace":"Windows.Networking","Name":"HostName"}},{"Name":"get_ConnectionServiceName","Static":false,"ReturnType":{"Kind":"Native","Name":"String"}},{"Name":"get_ServiceId","Static":false,"ReturnType":{"Namespace":"Windows.Devices.Bluetooth.Rfcomm","Name":"RfcommServiceId"}},{"Name":"get_ProtectionLevel","Static":false,"ReturnType":{"Namespace":"Windows.Networking.Sockets","Name":"SocketProtectionLevel"}},{"Name":"get_MaxProtectionLevel","Static":false,"ReturnType":{"Namespace":"Windows.Networking.Sockets","Name":"SocketProtectionLevel"}},{"Name":"GetSdpRawAttributesAsync","Static":false,"ReturnType":{"Namespace":"Windows.Foundation","Name":"IAsyncOperation","GenericArguments":[{"Namespace":"Windows.Foundation.Collections","Name":"IMapView","GenericArguments":[{"Kind":"Native","Name":"UInt32"},{"Namespace":"Windows.Storage.Streams","Name":"IBuffer"}]}]}},{"Name":"GetSdpRawAttributesAsync","Static":false,"Parameters":[{"Name":"cacheMode","Type":{"Namespace":"Windows.Devices.Bluetooth","Name":"BluetoothCacheMode"},"Attributes":["In"]}],"ReturnType":{"Namespace":"Windows.Foundation","Name":"IAsyncOperation","GenericArguments":[{"Namespace":"Windows.Foundation.Collections","Name":"IMapView","GenericArguments":[{"Kind":"Native","Name":"UInt32"},{"Namespace":"Windows.Storage.Streams","Name":"IBuffer"}]}]}}]},{"Kind":"Interface","Namespace":"Windows.Devices.Bluetooth.Rfcomm","Name":"IRfcommDeviceService2","Guid":"536ced14-ebcd-49fe-bf9f-40efc689b20d","Agile":false,"Interfaces":[{"Name":"IRfcommDeviceService","Namespace":"Windows.Devices.Bluetooth.Rfcomm"}],"Properties":[{"Name":"Device","Type":{"Namespace":"Windows.Devices.Bluetooth","Name":"BluetoothDevice"},"Accessors":["Getter"]}],"Methods":[{"Name":"get_Device","Static":false,"ReturnType":{"Namespace":"Windows.Devices.Bluetooth","Name":"BluetoothDevice"}}]},{"Kind":"Interface","Namespace":"Windows.Devices.Bluetooth.Rfcomm","Name":"IRfcommDeviceService3","Guid":"1c22ace6-dd44-4d23-866d-8f3486ee6490","Agile":false,"Interfaces":[{"Name":"IRfcommDeviceService2","Namespace":"Windows.Devices.Bluetooth.Rfcomm"},{"Name":"IRfcommDeviceService","Namespace":"Windows.Devices.Bluetooth.Rfcomm"}],"Properties":[{"Name":"DeviceAccessInformation","Type":{"Namespace":"Windows.Devices.Enumeration","Name":"DeviceAccessInformation"},"Accessors":["Getter"]}],"Methods":[{"Name":"get_DeviceAccessInformation","Static":false,"ReturnType":{"Namespace":"Windows.Devices.Enumeration","Name":"DeviceAccessInformation"}},{"Name":"RequestAccessAsync","Static":false,"ReturnType":{"Namespace":"Windows.Foundation","Name":"IAsyncOperation","GenericArguments":[{"Namespace":"Windows.Devices.Enumeration","Name":"DeviceAccessStatus"}]}}]},{"Kind":"Interface","Namespace":"Windows.Devices.Bluetooth.Rfcomm","Name":"IRfcommDeviceServiceStatics","Guid":"a4a149ef-626d-41ac-b253-87ac5c27e28a","Agile":false,"Methods":[{"Name":"FromIdAsync","Static":false,"Parameters":[{"Name":"deviceId","Type":{"Kind":"Native","Name":"String"},"Attributes":["In"]}],"ReturnType":{"Namespace":"Windows.Foundation","Name":"IAsyncOperation","GenericArguments":[{"Namespace":"Windows.Devices.Bluetooth.Rfcomm","Name":"RfcommDeviceService"}]}},{"Name":"GetDeviceSelector","Static":false,"Parameters":[{"Name":"serviceId","Type":{"Namespace":"Windows.Devices.Bluetooth.Rfcomm","Name":"RfcommServiceId"},"Attributes":["In"]}],"ReturnType":{"Kind":"Native","Name":"String"}}]},{"Kind":"Interface","Namespace":"Windows.Devices.Bluetooth.Rfcomm","Name":"IRfcommDeviceServiceStatics2","Guid":"aa8cb1c9-e78d-4be4-8076-0a3d87a0a05f","Agile":false,"Interfaces":[{"Name":"IRfcommDeviceServiceStatics","Namespace":"Windows.Devices.Bluetooth.Rfcomm"}],"Methods":[{"Name":"GetDeviceSelectorForBluetoothDevice","Static":false,"Parameters":[{"Name":"bluetoothDevice","Type":{"Namespace":"Windows.Devices.Bluetooth","Name":"BluetoothDevice"},"Attributes":["In"]}],"ReturnType":{"Kind":"Native","Name":"String"}},{"Name":"GetDeviceSelectorForBluetoothDevice","Static":false,"Parameters":[{"Name":"bluetoothDevice","Type":{"Namespace":"Windows.Devices.Bluetooth","Name":"BluetoothDevice"},"Attributes":["In"]},{"Name":"cacheMode","Type":{"Namespace":"Windows.Devices.Bluetooth","Name":"BluetoothCacheMode"},"Attributes":["In"]}],"ReturnType":{"Kind":"Native","Name":"String"}},{"Name":"GetDeviceSelectorForBluetoothDeviceAndServiceId","Static":false,"Parameters":[{"Name":"bluetoothDevice","Type":{"Namespace":"Windows.Devices.Bluetooth","Name":"BluetoothDevice"},"Attributes":["In"]},{"Name":"serviceId","Type":{"Namespace":"Windows.Devices.Bluetooth.Rfcomm","Name":"RfcommServiceId"},"Attributes":["In"]}],"ReturnType":{"Kind":"Native","Name":"String"}},{"Name":"GetDeviceSelectorForBluetoothDeviceAndServiceId","Static":false,"Parameters":[{"Name":"bluetoothDevice","Type":{"Namespace":"Windows.Devices.Bluetooth","Name":"BluetoothDevice"},"Attributes":["In"]},{"Name":"serviceId","Type":{"Namespace":"Windows.Devices.Bluetooth.Rfcomm","Name":"RfcommServiceId"},"Attributes":["In"]},{"Name":"cacheMode","Type":{"Namespace":"Windows.Devices.Bluetooth","Name":"BluetoothCacheMode"},"Attributes":["In"]}],"ReturnType":{"Kind":"Native","Name":"String"}}]},{"Kind":"Interface","Namespace":"Windows.Devices.Bluetooth.Rfcomm","Name":"IRfcommDeviceServicesResult","Guid":"3b48388c-7ccf-488e-9625-d259a5732d55","Agile":false,"Properties":[{"Name":"Error","Type":{"Namespace":"Windows.Devices.Bluetooth","Name":"BluetoothError"},"Accessors":["Getter"]},{"Name":"Services","Type":{"Namespace":"Windows.Foundation.Collections","Name":"IVectorView","GenericArguments":[{"Namespace":"Windows.Devices.Bluetooth.Rfcomm","Name":"RfcommDeviceService"}]},"Accessors":["Getter"]}],"Methods":[{"Name":"get_Error","Static":false,"ReturnType":{"Namespace":"Windows.Devices.Bluetooth","Name":"BluetoothError"}},{"Name":"get_Services","Static":false,"ReturnType":{"Namespace":"Windows.Foundation.Collections","Name":"IVectorView","GenericArguments":[{"Namespace":"Windows.Devices.Bluetooth.Rfcomm","Name":"RfcommDeviceService"}]}}]},{"Kind":"Interface","Namespace":"Windows.Devices.Bluetooth.Rfcomm","Name":"IRfcommServiceId","Guid":"22629204-7e02-4017-8136-da1b6a1b9bbf","Agile":false,"Properties":[{"Name":"Uuid","Type":{"Namespace":"System","Name":"Guid"},"Accessors":["Getter"]}],"Methods":[{"Name":"get_Uuid","Static":false,"ReturnType":{"Namespace":"System","Name":"Guid"}},{"Name":"AsShortId","Static":false,"ReturnType":{"Kind":"Native","Name":"UInt32"}},{"Name":"AsString","Static":false,"ReturnType":{"Kind":"Native","Name":"String"}}]},{"Kind":"Interface","Namespace":"Windows.Devices.Bluetooth.Rfcomm","Name":"IRfcommServiceIdStatics","Guid":"2a179eba-a975-46e3-b56b-08ffd783a5fe","Agile":false,"Properties":[{"Name":"GenericFileTransfer","Type":{"Namespace":"Windows.Devices.Bluetooth.Rfcomm","Name":"RfcommServiceId"},"Accessors":["Getter"]},{"Name":"ObexFileTransfer","Type":{"Namespace":"Windows.Devices.Bluetooth.Rfcomm","Name":"RfcommServiceId"},"Accessors":["Getter"]},{"Name":"ObexObjectPush","Type":{"Namespace":"Windows.Devices.Bluetooth.Rfcomm","Name":"RfcommServiceId"},"Accessors":["Getter"]},{"Name":"PhoneBookAccessPce","Type":{"Namespace":"Windows.Devices.Bluetooth.Rfcomm","Name":"RfcommServiceId"},"Accessors":["Getter"]},{"Name":"PhoneBookAccessPse","Type":{"Namespace":"Windows.Devices.Bluetooth.Rfcomm","Name":"RfcommServiceId"},"Accessors":["Getter"]},{"Name":"SerialPort","Type":{"Namespace":"Windows.Devices.Bluetooth.Rfcomm","Name":"RfcommServiceId"},"Accessors":["Getter"]}],"Methods":[{"Name":"FromUuid","Static":false,"Parameters":[{"Name":"uuid","Type":{"Namespace":"System","Name":"Guid"},"Attributes":["In"]}],"ReturnType":{"Namespace":"Windows.Devices.Bluetooth.Rfcomm","Name":"RfcommServiceId"}},{"Name":"FromShortId","Static":false,"Parameters":[{"Name":"shortId","Type":{"Kind":"Native","Name":"UInt32"},"Attributes":["In"]}],"ReturnType":{"Namespace":"Windows.Devices.Bluetooth.Rfcomm","Name":"RfcommServiceId"}},{"Name":"get_SerialPort","Static":false,"ReturnType":{"Namespace":"Windows.Devices.Bluetooth.Rfcomm","Name":"RfcommServiceId"}},{"Name":"get_ObexObjectPush","Static":false,"ReturnType":{"Namespace":"Windows.Devices.Bluetooth.Rfcomm","Name":"RfcommServiceId"}},{"Name":"get_ObexFileTransfer","Static":false,"ReturnType":{"Namespace":"Windows.Devices.Bluetooth.Rfcomm","Name":"RfcommServiceId"}},{"Name":"get_PhoneBookAccessPce","Static":false,"ReturnType":{"Namespace":"Windows.Devices.Bluetooth.Rfcomm","Name":"RfcommServiceId"}},{"Name":"get_PhoneBookAccessPse","Static":false,"ReturnType":{"Namespace":"Windows.Devices.Bluetooth.Rfcomm","Name":"RfcommServiceId"}},{"Name":"get_GenericFileTransfer","Static":false,"ReturnType":{"Namespace":"Windows.Devices.Bluetooth.Rfcomm","Name":"RfcommServiceId"}}]},{"Kind":"Interface","Namespace":"Windows.Devices.Bluetooth.Rfcomm","Name":"IRfcommServiceProvider","Guid":"eadbfdc4-b1f6-44ff-9f7c-e7a82ab86821","Agile":false,"Properties":[{"Name":"SdpRawAttributes","Type":{"Namespace":"Windows.Foundation.Collections","Name":"IMap","GenericArguments":[{"Kind":"Native","Name":"UInt32"},{"Namespace":"Windows.Storage.Streams","Name":"IBuffer"}]},"Accessors":["Getter"]},{"Name":"ServiceId","Type":{"Namespace":"Windows.Devices.Bluetooth.Rfcomm","Name":"RfcommServiceId"},"Accessors":["Getter"]}],"Methods":[{"Name":"get_ServiceId","Static":false,"ReturnType":{"Namespace":"Windows.Devices.Bluetooth.Rfcomm","Name":"RfcommServiceId"}},{"Name":"get_SdpRawAttributes","Static":false,"ReturnType":{"Namespace":"Windows.Foundation.Collections","Name":"IMap","GenericArguments":[{"Kind":"Native","Name":"UInt32"},{"Namespace":"Windows.Storage.Streams","Name":"IBuffer"}]}},{"Name":"StartAdvertising","Static":false,"Parameters":[{"Name":"listener","Type":{"Namespace":"Windows.Networking.Sockets","Name":"StreamSocketListener"},"Attributes":["In"]}],"ReturnType":{"Kind":"Native","Name":"Void"}},{"Name":"StopAdvertising","Static":false,"ReturnType":{"Kind":"Native","Name":"Void"}}]},{"Kind":"Interface","Namespace":"Windows.Devices.Bluetooth.Rfcomm","Name":"IRfcommServiceProvider2","Guid":"736bdfc6-3c81-4d1e-baf2-ddbb81284512","Agile":false,"Interfaces":[{"Name":"IRfcommServiceProvider","Namespace":"Windows.Devices.Bluetooth.Rfcomm"}],"Methods":[{"Name":"StartAdvertising","Static":false,"Parameters":[{"Name":"listener","Type":{"Namespace":"Windows.Networking.Sockets","Name":"StreamSocketListener"},"Attributes":["In"]},{"Name":"radioDiscoverable","Type":{"Kind":"Native","Name":"Boolean"},"Attributes":["In"]}],"ReturnType":{"Kind":"Native","Name":"Void"}}]},{"Kind":"Interface","Namespace":"Windows.Devices.Bluetooth.Rfcomm","Name":"IRfcommServiceProviderStatics","Guid":"98888303-69ca-413a-84f7-4344c7292997","Agile":false,"Methods":[{"Name":"CreateAsync","Static":false,"Parameters":[{"Name":"serviceId","Type":{"Namespace":"Windows.Devices.Bluetooth.Rfcomm","Name":"RfcommServiceId"},"Attributes":["In"]}],"ReturnType":{"Namespace":"Windows.Foundation","Name":"IAsyncOperation","GenericArguments":[{"Namespace":"Windows.Devices.Bluetooth.Rfcomm","Name":"RfcommServiceProvider"}]}}]},{"Kind":"Class","Namespace":"Windows.Devices.Bluetooth.Rfcomm","Name":"RfcommDeviceService","Agile":true,"BaseType":{"Namespace":"System","Name":"Object"},"Factory":{"Statics":[{"Name":"IRfcommDeviceServiceStatics","Namespace":"Windows.Devices.Bluetooth.Rfcomm"},{"Name":"IRfcommDeviceServiceStatics2","Namespace":"Windows.Devices.Bluetooth.Rfcomm"}],"HasDefault":false},"DefaultInterface":{"Name":"IRfcommDeviceService","Namespace":"Windows.Devices.Bluetooth.Rfcomm"},"Interfaces":[{"Name":"IRfcommDeviceService","Namespace":"Windows.Devices.Bluetooth.Rfcomm"},{"Name":"IRfcommDeviceService2","Namespace":"Windows.Devices.Bluetooth.Rfcomm"},{"Name":"IClosable","Namespace":"Windows.Foundation"},{"Name":"IRfcommDeviceService3","Namespace":"Windows.Devices.Bluetooth.Rfcomm"}],"Properties":[{"Name":"ConnectionHostName","Type":{"Namespace":"Windows.Networking","Name":"HostName"},"Accessors":["Getter"]},{"Name":"ConnectionServiceName","Type":{"Kind":"Native","Name":"String"},"Accessors":["Getter"]},{"Name":"MaxProtectionLevel","Type":{"Namespace":"Windows.Networking.Sockets","Name":"SocketProtectionLevel"},"Accessors":["Getter"]},{"Name":"ProtectionLevel","Type":{"Namespace":"Windows.Networking.Sockets","Name":"SocketProtectionLevel"},"Accessors":["Getter"]},{"Name":"ServiceId","Type":{"Namespace":"Windows.Devices.Bluetooth.Rfcomm","Name":"RfcommServiceId"},"Accessors":["Getter"]},{"Name":"Device","Type":{"Namespace":"Windows.Devices.Bluetooth","Name":"BluetoothDevice"},"Accessors":["Getter"]},{"Name":"DeviceAccessInformation","Type":{"Namespace":"Windows.Devices.Enumeration","Name":"DeviceAccessInformation"},"Accessors":["Getter"]}],"Methods":[{"Name":"get_ConnectionHostName","Static":false,"ReturnType":{"Namespace":"Windows.Networking","Name":"HostName"}},{"Name":"get_ConnectionServiceName","Static":false,"ReturnType":{"Kind":"Native","Name":"String"}},{"Name":"get_ServiceId","Static":false,"ReturnType":{"Namespace":"Windows.Devices.Bluetooth.Rfcomm","Name":"RfcommServiceId"}},{"Name":"get_ProtectionLevel","Static":false,"ReturnType":{"Namespace":"Windows.Networking.Sockets","Name":"SocketProtectionLevel"}},{"Name":"get_MaxProtectionLevel","Static":false,"ReturnType":{"Namespace":"Windows.Networking.Sockets","Name":"SocketProtectionLevel"}},{"Name":"GetSdpRawAttributesAsync","Static":false,"ReturnType":{"Namespace":"Windows.Foundation","Name":"IAsyncOperation","GenericArguments":[{"Namespace":"Windows.Foundation.Collections","Name":"IMapView","GenericArguments":[{"Kind":"Native","Name":"UInt32"},{"Namespace":"Windows.Storage.Streams","Name":"IBuffer"}]}]}},{"Name":"GetSdpRawAttributesAsync","Static":false,"Parameters":[{"Name":"cacheMode","Type":{"Namespace":"Windows.Devices.Bluetooth","Name":"BluetoothCacheMode"},"Attributes":["In"]}],"ReturnType":{"Namespace":"Windows.Foundation","Name":"IAsyncOperation","GenericArguments":[{"Namespace":"Windows.Foundation.Collections","Name":"IMapView","GenericArguments":[{"Kind":"Native","Name":"UInt32"},{"Namespace":"Windows.Storage.Streams","Name":"IBuffer"}]}]}},{"Name":"get_Device","Static":false,"ReturnType":{"Namespace":"Windows.Devices.Bluetooth","Name":"BluetoothDevice"}},{"Name":"Close","Static":false,"ReturnType":{"Kind":"Native","Name":"Void"}},{"Name":"get_DeviceAccessInformation","Static":false,"ReturnType":{"Namespace":"Windows.Devices.Enumeration","Name":"DeviceAccessInformation"}},{"Name":"RequestAccessAsync","Static":false,"ReturnType":{"Namespace":"Windows.Foundation","Name":"IAsyncOperation","GenericArguments":[{"Namespace":"Windows.Devices.Enumeration","Name":"DeviceAccessStatus"}]}},{"Name":"GetDeviceSelectorForBluetoothDevice","Static":true,"Parameters":[{"Name":"bluetoothDevice","Type":{"Namespace":"Windows.Devices.Bluetooth","Name":"BluetoothDevice"},"Attributes":["In"]}],"ReturnType":{"Kind":"Native","Name":"String"}},{"Name":"GetDeviceSelectorForBluetoothDevice","Static":true,"Parameters":[{"Name":"bluetoothDevice","Type":{"Namespace":"Windows.Devices.Bluetooth","Name":"BluetoothDevice"},"Attributes":["In"]},{"Name":"cacheMode","Type":{"Namespace":"Windows.Devices.Bluetooth","Name":"BluetoothCacheMode"},"Attributes":["In"]}],"ReturnType":{"Kind":"Native","Name":"String"}},{"Name":"GetDeviceSelectorForBluetoothDeviceAndServiceId","Static":true,"Parameters":[{"Name":"bluetoothDevice","Type":{"Namespace":"Windows.Devices.Bluetooth","Name":"BluetoothDevice"},"Attributes":["In"]},{"Name":"serviceId","Type":{"Namespace":"Windows.Devices.Bluetooth.Rfcomm","Name":"RfcommServiceId"},"Attributes":["In"]}],"ReturnType":{"Kind":"Native","Name":"String"}},{"Name":"GetDeviceSelectorForBluetoothDeviceAndServiceId","Static":true,"Parameters":[{"Name":"bluetoothDevice","Type":{"Namespace":"Windows.Devices.Bluetooth","Name":"BluetoothDevice"},"Attributes":["In"]},{"Name":"serviceId","Type":{"Namespace":"Windows.Devices.Bluetooth.Rfcomm","Name":"RfcommServiceId"},"Attributes":["In"]},{"Name":"cacheMode","Type":{"Namespace":"Windows.Devices.Bluetooth","Name":"BluetoothCacheMode"},"Attributes":["In"]}],"ReturnType":{"Kind":"Native","Name":"String"}},{"Name":"FromIdAsync","Static":true,"Parameters":[{"Name":"deviceId","Type":{"Kind":"Native","Name":"String"},"Attributes":["In"]}],"ReturnType":{"Namespace":"Windows.Foundation","Name":"IAsyncOperation","GenericArguments":[{"Namespace":"Windows.Devices.Bluetooth.Rfcomm","Name":"RfcommDeviceService"}]}},{"Name":"GetDeviceSelector","Static":true,"Parameters":[{"Name":"serviceId","Type":{"Namespace":"Windows.Devices.Bluetooth.Rfcomm","Name":"RfcommServiceId"},"Attributes":["In"]}],"ReturnType":{"Kind":"Native","Name":"String"}}]},{"Kind":"Class","Namespace":"Windows.Devices.Bluetooth.Rfcomm","Name":"RfcommDeviceServicesResult","Agile":true,"BaseType":{"Namespace":"System","Name":"Object"},"DefaultInterface":{"Name":"IRfcommDeviceServicesResult","Namespace":"Windows.Devices.Bluetooth.Rfcomm"},"Interfaces":[{"Name":"IRfcommDeviceServicesResult","Namespace":"Windows.Devices.Bluetooth.Rfcomm"}],"Properties":[{"Name":"Error","Type":{"Namespace":"Windows.Devices.Bluetooth","Name":"BluetoothError"},"Accessors":["Getter"]},{"Name":"Services","Type":{"Namespace":"Windows.Foundation.Collections","Name":"IVectorView","GenericArguments":[{"Namespace":"Windows.Devices.Bluetooth.Rfcomm","Name":"RfcommDeviceService"}]},"Accessors":["Getter"]}],"Methods":[{"Name":"get_Error","Static":false,"ReturnType":{"Namespace":"Windows.Devices.Bluetooth","Name":"BluetoothError"}},{"Name":"get_Services","Static":false,"ReturnType":{"Namespace":"Windows.Foundation.Collections","Name":"IVectorView","GenericArguments":[{"Namespace":"Windows.Devices.Bluetooth.Rfcomm","Name":"RfcommDeviceService"}]}}]},{"Kind":"Class","Namespace":"Windows.Devices.Bluetooth.Rfcomm","Name":"RfcommServiceId","Agile":true,"BaseType":{"Namespace":"System","Name":"Object"},"Factory":{"Statics":[{"Name":"IRfcommServiceIdStatics","Namespace":"Windows.Devices.Bluetooth.Rfcomm"}],"HasDefault":false},"DefaultInterface":{"Name":"IRfcommServiceId","Namespace":"Windows.Devices.Bluetooth.Rfcomm"},"Interfaces":[{"Name":"IRfcommServiceId","Namespace":"Windows.Devices.Bluetooth.Rfcomm"}],"Properties":[{"Name":"Uuid","Type":{"Namespace":"System","Name":"Guid"},"Accessors":["Getter"]},{"Name":"GenericFileTransfer","Type":{"Namespace":"Windows.Devices.Bluetooth.Rfcomm","Name":"RfcommServiceId"},"Accessors":["Getter"]},{"Name":"ObexFileTransfer","Type":{"Namespace":"Windows.Devices.Bluetooth.Rfcomm","Name":"RfcommServiceId"},"Accessors":["Getter"]},{"Name":"ObexObjectPush","Type":{"Namespace":"Windows.Devices.Bluetooth.Rfcomm","Name":"RfcommServiceId"},"Accessors":["Getter"]},{"Name":"PhoneBookAccessPce","Type":{"Namespace":"Windows.Devices.Bluetooth.Rfcomm","Name":"RfcommServiceId"},"Accessors":["Getter"]},{"Name":"PhoneBookAccessPse","Type":{"Namespace":"Windows.Devices.Bluetooth.Rfcomm","Name":"RfcommServiceId"},"Accessors":["Getter"]},{"Name":"SerialPort","Type":{"Namespace":"Windows.Devices.Bluetooth.Rfcomm","Name":"RfcommServiceId"},"Accessors":["Getter"]}],"Methods":[{"Name":"get_Uuid","Static":false,"ReturnType":{"Namespace":"System","Name":"Guid"}},{"Name":"AsShortId","Static":false,"ReturnType":{"Kind":"Native","Name":"UInt32"}},{"Name":"AsString","Static":false,"ReturnType":{"Kind":"Native","Name":"String"}},{"Name":"FromUuid","Static":true,"Parameters":[{"Name":"uuid","Type":{"Namespace":"System","Name":"Guid"},"Attributes":["In"]}],"ReturnType":{"Namespace":"Windows.Devices.Bluetooth.Rfcomm","Name":"RfcommServiceId"}},{"Name":"FromShortId","Static":true,"Parameters":[{"Name":"shortId","Type":{"Kind":"Native","Name":"UInt32"},"Attributes":["In"]}],"ReturnType":{"Namespace":"Windows.Devices.Bluetooth.Rfcomm","Name":"RfcommServiceId"}},{"Name":"get_SerialPort","Static":true,"ReturnType":{"Namespace":"Windows.Devices.Bluetooth.Rfcomm","Name":"RfcommServiceId"}},{"Name":"get_ObexObjectPush","Static":true,"ReturnType":{"Namespace":"Windows.Devices.Bluetooth.Rfcomm","Name":"RfcommServiceId"}},{"Name":"get_ObexFileTransfer","Static":true,"ReturnType":{"Namespace":"Windows.Devices.Bluetooth.Rfcomm","Name":"RfcommServiceId"}},{"Name":"get_PhoneBookAccessPce","Static":true,"ReturnType":{"Namespace":"Windows.Devices.Bluetooth.Rfcomm","Name":"RfcommServiceId"}},{"Name":"get_PhoneBookAccessPse","Static":true,"ReturnType":{"Namespace":"Windows.Devices.Bluetooth.Rfcomm","Name":"RfcommServiceId"}},{"Name":"get_GenericFileTransfer","Static":true,"ReturnType":{"Namespace":"Windows.Devices.Bluetooth.Rfcomm","Name":"RfcommServiceId"}}]},{"Kind":"Class","Namespace":"Windows.Devices.Bluetooth.Rfcomm","Name":"RfcommServiceProvider","Agile":true,"BaseType":{"Namespace":"System","Name":"Object"},"Factory":{"Statics":[{"Name":"IRfcommServiceProviderStatics","Namespace":"Windows.Devices.Bluetooth.Rfcomm"}],"HasDefault":false},"DefaultInterface":{"Name":"IRfcommServiceProvider","Namespace":"Windows.Devices.Bluetooth.Rfcomm"},"Interfaces":[{"Name":"IRfcommServiceProvider","Namespace":"Windows.Devices.Bluetooth.Rfcomm"},{"Name":"IRfcommServiceProvider2","Namespace":"Windows.Devices.Bluetooth.Rfcomm"}],"Properties":[{"Name":"SdpRawAttributes","Type":{"Namespace":"Windows.Foundation.Collections","Name":"IMap","GenericArguments":[{"Kind":"Native","Name":"UInt32"},{"Namespace":"Windows.Storage.Streams","Name":"IBuffer"}]},"Accessors":["Getter"]},{"Name":"ServiceId","Type":{"Namespace":"Windows.Devices.Bluetooth.Rfcomm","Name":"RfcommServiceId"},"Accessors":["Getter"]}],"Methods":[{"Name":"get_ServiceId","Static":false,"ReturnType":{"Namespace":"Windows.Devices.Bluetooth.Rfcomm","Name":"RfcommServiceId"}},{"Name":"get_SdpRawAttributes","Static":false,"ReturnType":{"Namespace":"Windows.Foundation.Collections","Name":"IMap","GenericArguments":[{"Kind":"Native","Name":"UInt32"},{"Namespace":"Windows.Storage.Streams","Name":"IBuffer"}]}},{"Name":"StartAdvertising","Static":false,"Parameters":[{"Name":"listener","Type":{"Namespace":"Windows.Networking.Sockets","Name":"StreamSocketListener"},"Attributes":["In"]}],"ReturnType":{"Kind":"Native","Name":"Void"}},{"Name":"StopAdvertising","Static":false,"ReturnType":{"Kind":"Native","Name":"Void"}},{"Name":"StartAdvertising","Static":false,"Parameters":[{"Name":"listener","Type":{"Namespace":"Windows.Networking.Sockets","Name":"StreamSocketListener"},"Attributes":["In"]},{"Name":"radioDiscoverable","Type":{"Kind":"Native","Name":"Boolean"},"Attributes":["In"]}],"ReturnType":{"Kind":"Native","Name":"Void"}},{"Name":"CreateAsync","Static":true,"Parameters":[{"Name":"serviceId","Type":{"Namespace":"Windows.Devices.Bluetooth.Rfcomm","Name":"RfcommServiceId"},"Attributes":["In"]}],"ReturnType":{"Namespace":"Windows.Foundation","Name":"IAsyncOperation","GenericArguments":[{"Namespace":"Windows.Devices.Bluetooth.Rfcomm","Name":"RfcommServiceProvider"}]}}]}]